LICENSE
tfads_o_builder/Line.py
tfads_o_builder/Point.py
tfads_o_builder/feature_types/ActiveDeletedCode.py
tfads_o_builder/feature_types/CompilationDate.py
tfads_o_builder/feature_types/ControlReleasabilityCode.py
tfads_o_builder/feature_types/CoordinatePrecisionFlag.py
tfads_o_builder/feature_types/CountryCode.py
tfads_o_builder/feature_types/DeficiencyCode.py
tfads_o_builder/feature_types/DeletingOrganization.py
tfads_o_builder/feature_types/DerivingOrganization.py
tfads_o_builder/feature_types/FACCCode.py
tfads_o_builder/feature_types/FACCName.py
tfads_o_builder/feature_types/FeatureTypeCode.py
tfads_o_builder/feature_types/FeatureTypeName.py
tfads_o_builder/feature_types/HeightAGLAccuracy.py
tfads_o_builder/feature_types/HeightAMSLAccuracy.py
tfads_o_builder/feature_types/HorizontalAccuracy.py
tfads_o_builder/feature_types/HorizontalDatum.py
tfads_o_builder/feature_types/Latitude.py
tfads_o_builder/feature_types/Lights.py
tfads_o_builder/feature_types/LocationElevation.py
tfads_o_builder/feature_types/LocationElevationAccuracy.py
tfads_o_builder/feature_types/Longitude.py
tfads_o_builder/feature_types/MultipleNumber.py
tfads_o_builder/feature_types/ObstructionHeightAGL.py
tfads_o_builder/feature_types/ObstructionHeightAMSL.py
tfads_o_builder/feature_types/OriginalID.py
tfads_o_builder/feature_types/OutputRemarks.py
tfads_o_builder/feature_types/PreviousVOIdentifierCode.py
tfads_o_builder/feature_types/ProcessCode.py
tfads_o_builder/feature_types/ProvinceCode.py
tfads_o_builder/feature_types/RevisionDate.py
tfads_o_builder/feature_types/SecurityClassification.py
tfads_o_builder/feature_types/SingleMultipleFlag.py
tfads_o_builder/feature_types/SourceDate.py
tfads_o_builder/feature_types/SurfaceMaterialCode.py
tfads_o_builder/feature_types/TransactionType.py
tfads_o_builder/feature_types/UUID.py
tfads_o_builder/feature_types/VOIdentification.py
tfads_o_builder/feature_types/VOSequenceNumber.py
tfads_o_builder/feature_types/ValidationCode.py
tfads_o_builder-0.0.261.dist-info/LICENSE
tfads_o_builder-0.0.261.dist-info/METADATA
tfads_o_builder-0.0.261.dist-info/WHEEL
tfads_o_builder-0.0.261.dist-info/RECORD
