Metadata-Version: 2.1
Name: tfads-o-builder
Version: 0.0.261
Summary: Helper functions used to build data as tfads-o format.
Home-page: https://github.com/fsai-dev/fsai-cli-tools
License: MIT
Author: Michael Mohamed
Author-email: michael@foundationstack.com
Requires-Python: >=3.8,<3.12
Classifier: License :: OSI Approved :: MIT License
Classifier: Programming Language :: Python :: 3
Classifier: Programming Language :: Python :: 3.8
Classifier: Programming Language :: Python :: 3.9
Classifier: Programming Language :: Python :: 3.10
Classifier: Programming Language :: Python :: 3.11
Requires-Dist: beartype (>=0.16.4,<0.17.0)
Requires-Dist: loguru (>=0.6.0,<0.7.0)
Project-URL: Repository, https://github.com/fsai-dev/fsai-cli-tools
